csvtool/__init__.py
csvtool/csvtool.py
csvtool-0.2.dist-info/LICENSE
csvtool-0.2.dist-info/METADATA
csvtool-0.2.dist-info/WHEEL
csvtool-0.2.dist-info/entry_points.txt
csvtool-0.2.dist-info/top_level.txt
csvtool-0.2.dist-info/RECORD
